CHANGES.md
LICENSE.AGPL.md
LICENSE.md
MANIFEST.in
README.md
VERSION
setup.cfg
setup.py
bin/rc.stack
src/rc.io.egg-info/PKG-INFO
src/rc.io.egg-info/SOURCES.txt
src/rc.io.egg-info/dependency_links.txt
src/rc.io.egg-info/namespace_packages.txt
src/rc.io.egg-info/not-zip-safe
src/rc.io.egg-info/requires.txt
src/rc.io.egg-info/top_level.txt
src/rc/io/SDIST
src/rc/io/VERSION
src/rc/io/__init__.py
src/rc/io/named_pipe.py
src/rc/io/stream.py
src/rc/io/tcp_socket.py
src/rc/io/uds_socket.py
tests/unit_tests/test_named_pipes.py
tests/unit_tests/test_uds.py